{
	"backtrace" : 3,
	"backtraceGraph" : 
	{
		"commands" : 
		[
			"add_custom_target",
			"_juce_configure_plugin_targets",
			"juce_add_plugin",
			"add_dependencies",
			"_juce_link_plugin_wrapper"
		],
		"files" : 
		[
			"libs/juce/extras/Build/CMake/JUCEUtils.cmake",
			"plugin/CMakeLists.txt"
		],
		"nodes" : 
		[
			{
				"file" : 1
			},
			{
				"command" : 2,
				"file" : 1,
				"line" : 11,
				"parent" : 0
			},
			{
				"command" : 1,
				"file" : 0,
				"line" : 2190,
				"parent" : 1
			},
			{
				"command" : 0,
				"file" : 0,
				"line" : 1593,
				"parent" : 2
			},
			{
				"command" : 4,
				"file" : 0,
				"line" : 1597,
				"parent" : 2
			},
			{
				"command" : 3,
				"file" : 0,
				"line" : 1452,
				"parent" : 4
			},
			{
				"command" : 4,
				"file" : 0,
				"line" : 1597,
				"parent" : 2
			},
			{
				"command" : 3,
				"file" : 0,
				"line" : 1452,
				"parent" : 6
			}
		]
	},
	"dependencies" : 
	[
		{
			"backtrace" : 5,
			"id" : "AudioPlugin_Standalone::@26efe8164589a77d2096"
		},
		{
			"backtrace" : 7,
			"id" : "AudioPlugin_VST3::@26efe8164589a77d2096"
		}
	],
	"folder" : 
	{
		"name" : "AudioPlugin"
	},
	"id" : "AudioPlugin_All::@26efe8164589a77d2096",
	"name" : "AudioPlugin_All",
	"paths" : 
	{
		"build" : "plugin",
		"source" : "plugin"
	},
	"sources" : [],
	"type" : "UTILITY"
}
